RV32I/Core/ALU.v
module ALU (A,B, Result, ALUControl, OverFlow, Carry, Zero, Negative);

input [31:0] A,B;
input [2:0] ALUControl;
output OverFlow,Carry,Zero,Negative;
output [31:0] Result;

wire Cout;
wire [31:0] Sum;

  assign Sum = (ALUControl[0] == 1'b0) ? A + B :(A + ((~B)+1)) ;
  
    assign {Cout,Result} = (ALUControl == 3'b000) ? Sum :
                           (ALUControl == 3'b001) ? Sum :
                           (ALUControl == 3'b010) ? A & B :
                           (ALUControl == 3'b011) ? A | B :
                           (ALUControl == 3'b101) ? {{32{1'b0}},(Sum[31])} :
                           {33{1'b0}};

    assign OverFlow = ((Sum[31] ^ A[31]) & (~(ALUControl[0] ^ B[31] ^ A[31])) & (~ALUControl[1]));

    assign Carry = ((~ALUControl[1]) & Cout);

    assign Zero = &(~Result); // All bits  = to 0
    assign Negative = Result[31]; //MSB==1

endmodule

RV32I/Test Bench/ALU_tb.v
`timescale 1ns/1ns
`include "ALU.v"

module ALU_tb;

  // Inputs
  reg [31:0] A;
  reg [31:0] B;
  reg [2:0] ALUControl;

  // Outputs
  wire [31:0] Result;
  wire Carry, OverFlow, Zero, Negative;

  ALU uut (
    .A(A),
    .B(B),
    .ALUControl(ALUControl),
    .Result(Result),
    .Carry(Carry),
    .OverFlow(OverFlow),
    .Zero(Zero),
    .Negative(Negative)
  );

  initial begin
    $dumpfile("ALU_tb.vcd");
    $dumpvars(0, ALU_tb);

    $display("Starting ALU testbench...");

    // Test ADD: 2 + 2 = 4
    A = 32'd2;
    B = 32'd2;
    ALUControl = 3'b000; 
    #20;

    // Test SUB: 5 - 2 = 3
    A = 32'd5;
    B = 32'd2;
    ALUControl = 3'b001; 
    #20;

    // Test AND: 5 & 3 = 1
    A = 32'd5;
    B = 32'd3;
    ALUControl = 3'b010; 
    #20;

    // Test OR: 5 | 2 = 7
    A = 32'd5;
    B = 32'd2;
    ALUControl = 3'b011; 
    #20;

    // Test SLT: 2 < 5 → 1
    A = 32'd2;
    B = 32'd5;
    ALUControl = 3'b101; 
    #20;

    // Test SLT: 5 < 2 → 0
    A = 32'd5;
    B = 32'd2;
    ALUControl = 3'b101; 
    #20;

    // Test ADD overflow: 2^31 - 1 + 1
    A = 32'h7FFFFFFF;
    B = 32'd1;
    ALUControl = 3'b000; 
    #20;

    // Test SUB overflow: -2^31 - 1
    A = 32'h80000000;
    B = 32'd1;
    ALUControl = 3'b001; 
    #20;

    $display("ALU test complete.");
    $finish;
  end

endmodule

RV32I/Test Bench/ALU_tb.vcd
$date
	Wed Jul  2 20:47:48 2025
$end
$version
	Icarus Verilog
$end
$timescale
	1ns
$end
$scope module ALU_tb $end
$var wire 1 ! Zero $end
$var wire 32 " Result [31:0] $end
$var wire 1 # OverFlow $end
$var wire 1 $ Negative $end
$var wire 1 % Carry $end
$var reg 32 & A [31:0] $end
$var reg 3 ' ALUControl [2:0] $end
$var reg 32 ( B [31:0] $end
$scope module uut $end
$var wire 32 ) A [31:0] $end
$var wire 3 * ALUControl [2:0] $end
$var wire 32 + B [31:0] $end
$var wire 1 % Carry $end
$var wire 1 # OverFlow $end
$var wire 1 ! Zero $end
$var wire 32 , Sum [31:0] $end
$var wire 32 - Result [31:0] $end
$var wire 1 $ Negative $end
$var wire 1 . Cout $end
$upscope $end
$upscope $end
$enddefinitions $end
$comment Show the parameter values. $end
$dumpall
$end
#0
$dumpvars
0.
b100 -
b100 ,
b10 +
b0 *
b10 )
b10 (
b0 '
b10 &
0%
0$
0#
b100 "
0!
$end
#20
b11 "
b11 -
b11 ,
b1 '
b1 *
b101 &
b101 )
#40
0!
b1 "
b1 -
b1000 ,
b10 '
b10 *
b11 (
b11 +
#60
b111 "
b111 -
b11 ,
b11 '
b11 *
b10 (
b10 +
#80
0!
b1 "
b1 -
b11111111111111111111111111111101 ,
b101 '
b101 *
b101 (
b101 +
b10 &
b10 )
#100
1!
b0 "
b0 -
b11 ,
b10 (
b10 +
b101 &
b101 )
#120
1$
1#
0!
b10000000000000000000000000000000 "
b10000000000000000000000000000000 -
b10000000000000000000000000000000 ,
b0 '
b0 *
b1 (
b1 +
b1111111111111111111111111111111 &
b1111111111111111111111111111111 )
#140
0$
b1111111111111111111111111111111 "
b1111111111111111111111111111111 -
1#
b1111111111111111111111111111111 ,
b1 '
b1 *
b10000000000000000000000000000000 &
b10000000000000000000000000000000 )
